pyopen_wakeword/__init__.py
pyopen_wakeword/__main__.py
pyopen_wakeword/const.py
pyopen_wakeword/openwakeword.py
pyopen_wakeword/wakeword.py
pyopen_wakeword/lib/libtensorflowlite_c.so
pyopen_wakeword/models/alexa.tflite
pyopen_wakeword/models/embedding_model.tflite
pyopen_wakeword/models/hey_jarvis.tflite
pyopen_wakeword/models/hey_mycroft.tflite
pyopen_wakeword/models/hey_rhasspy.tflite
pyopen_wakeword/models/melspectrogram.tflite
pyopen_wakeword/models/okay_nabu.tflite
pyopen_wakeword-1.0.1.dist-info/METADATA
pyopen_wakeword-1.0.1.dist-info/WHEEL
pyopen_wakeword-1.0.1.dist-info/top_level.txt
pyopen_wakeword-1.0.1.dist-info/RECORD
pyopen_wakeword-1.0.1.dist-info/licenses/LICENSE
